Workbook

Sheet Cover
B2: MidWest Precision Components, Inc.
B3: FP&A Integrated Financial Model — FY2025A Actuals through FY2028 Long-Range Plan
B6: Contents
B7: Control Panel | C7: Scenario selector and model-wide settings
B8: Historical_Actuals | C8: 2025A baseline P&L and operating summary
B9: Assumptions / FX_Assumptions | C9: Key growth, margin, working-capital, and FX drivers by year
B10: Revenue_Model | C10: Unit / ASP build by product line
B11: Production_Model / Sourcing_Model | C11: Production volumes, scrap/yield, and material sourcing (with FX)
B12: Direct_Labor / Manufacturing_OH | C12: Factory labor and manufacturing overhead build
B13: Headcount / OpEx / CapEx | C13: Corporate payroll, operating expenses, and capital spending
B14: Working_Capital | C14: AR / Inventory / AP and cash conversion cycle
B15: P&L / Cash_Flow | C15: Consolidated income statement and statement of cash flows
B16: Budget_vs_Actual / Variance_Drivers | C16: 2026 Budget-to-Forecast variance and driver bridge
B17: Forecast | C17: 4-year summary trend of key metrics
B18: Scenario_Analysis | C18: Base / Upside / Downside sensitivity, linked to Control Panel
... B20: Checks | C20: Model integrity and tie-out checks

Sheet Dashboard
A1: Row Labels | B1: Sum of 2025 Revenue | C1: Sum of 2026 Revenue | D1: Sum of 2026 Forecast Revenue | E1: Sum of 2027 Revenue | F1: Sum of 2028 Revenue
A2: Automotive Components | B2: 10850000 | C2: 11510765 | D2: 11399281 | E2: 12270475 | F2: 12577237
A3: Industrial Assemblies | B3: 16900000 | C3: 17929210 | D3: 17755562 | E3: 19112538 | F3: 19590351
A4: Precision Components | B4: 22200000 | C4: 23551980 | D4: 23323875 | E4: 25106411 | F4: 25734071
A5: Grand Total | B5: 49950000 | C5: 52991955 | D5: 52478719 | E5: 56489424 | F5: 57901660

Sheet Control Panel
B1: MidWest Precision Components, Inc.
B2: FP&A Control Panel
B4: Selected Scenario | C4: Upside
B5: Reporting Currency | C5: USD
B6: Historical Year | C6: 2025
B7: Budget Year | C7: 2026
B8: Forecast Year | C8: 2026
B9: Long-Range Plan Year 1 | C9: 2027
B10: Long-Range Plan Year 2 | C10: 2028
B11: Model Version | C11: v1.0

Sheet Historical_Actuals
B1: MidWest Precision Components, Inc.
B2: 2025A Historical Summary (Baseline Year)
B4: P&L Summary
B5: Revenue | C5: ='P&L'!B5 -> 49950000
B6: Cost of Goods Sold | C6: ='P&L'!B6 -> 34465500
B7: Gross Profit | C7: ='P&L'!B7 -> 15484500
B8: Gross Margin % | C8: ='P&L'!B8 -> 0.31
B9: Total Operating Expenses | C9: ='P&L'!B11 -> 7378000
B10: EBITDA | C10: ='P&L'!B12 -> 8106500
B11: EBITDA Margin % | C11: ='P&L'!B13 -> 0.16229229
B12: EBIT | C12: ='P&L'!B18 -> 7906500
B13: Net Income | C13: ='P&L'!B20 -> 5929875
B14: Net Margin % | C14: ='P&L'!B21 -> 0.11871622
B16: Operating Metrics
B17: Total Units Sold | C17: =Revenue_Model!C8 -> 247000
B18: Total Production Units | C18: =Production_Model!F8 -> 253333.33
B19: Total Headcount | C19: =Headcount!B12 -> 60
B20: Total CapEx | C20: =CapEx!B10 -> 1750000
B21: CapEx % of Revenue | C21: =CapEx!B16 -> 0.035035035
B22: Capacity Utilization | C22: =CapEx!B18 -> 0.9047619

Sheet Assumptions
B1: MidWest Precision Components, Inc.
B2: Assumptions
B4: Driver | C4: 2025A | D4: 2026 Budget | E4: 2026 Forecast | F4: 2027 Plan | G4: 2028 Plan
B5: Revenue Growth | C5: — | D5: 0.06 | E5: 0.05 | F5: 0.07 | G5: 0.06
B6: ASP Growth | C6: — | D6: 0.03 | E6: 0.025 | F6: 0.03 | G6: 0.03
B7: Volume Growth | C7: — | D7: 0.03 | E7: 0.025 | F7: 0.04 | G7: 0.03
B8: Gross Margin | C8: 0.31 | D8: 0.32 | E8: 0.31 | F8: 0.325 | G8: 0.335
B9: Scrap / Yield Loss | C9: 0.025 | D9: 0.024 | E9: 0.026 | F9: 0.023 | G9: 0.022
B10: Salary Increase | C10: — | D10: 0.04 | E10: 0.04 | F10: 0.035 | G10: 0.035
B11: Benefits % Payroll | C11: 0.22 | D11: 0.22 | E11: 0.22 | F11: 0.22 | G11: 0.22
B12: DSO | C12: 48 | D12: 47 | E12: 49 | F12: 46 | G12: 45
B13: DIO | C13: 62 | D13: 60 | E13: 64 | F13: 59 | G13: 57
B14: DPO | C14: 42 | D14: 43 | E14: 44 | F14: 43 | G14: 42
B15: CapEx % Revenue | C15: 0.035 | D15: 0.04 | E15: 0.045 | F15: 0.04 | G15: 0.038
B16: Tax Rate | C16: 0.25 | D16: 0.25 | E16: 0.25 | F16: 0.25 | G16: 0.25

Sheet FX_Assumptions
C1: MidWest Precision Components, Inc.
C2: FX Assumptions
C4: Currency Pair | D4: 2025A | E4: 2026 Budget | F4: 2026 Forecast | G4: 2027 Plan | H4: 2028 Plan
C5: EUR/USD | D5: 1.08 | E5: 1.1 | F5: 1.09 | G5: 1.11 | H5: 1.12
C6: CNY/USD | D6: 0.138 | E6: 0.14 | F6: 0.139 | G6: 0.142 | H6: 0.145

Sheet Revenue_Model
B1: MidWest Precision Components, Inc.
B2: Assume 3.0% ASP growth
B4: Product | C4: 2025 Units | D4: 2025 ASP | E4: 2025 Revenue | F4: 2026 Units | G4: 2026 ASP | H4: 2026 Revenue | I4: 2026 Forecast Units | J4: 2026 Forecast ASP | K4: 2026 Forecast Revenue | L4: 2027 Units | M4: 2027 ASP | N4: 2027 Revenue | O4: 2028 Units | P4: 2028 ASP | Q4: 2028 Revenue
B5: Precision Components | C5: 120000 | D5: 185 | E5: =C5*D5 -> 22200000 | F5: =C5*(1+Assumptions!$D$7) -> 123600 | G5: =D5*(1+Assumptions!$D$6) -> 190.55 | H5: =F5*G5 -> 23551980 | I5: =C5*(1+Assumptions!$E$6) -> 123000 | J5: =D5*(1+Assumptions!$E$6) -> 189.625 | K5: =I5*J5 -> 23323875 | L5: =I5*(1+Assumptions!$F$7) -> 127920 | M5: =G5*(1+Assumptions!$F$6) -> 196.2665 | N5: =L5*M5 -> 25106411 | O5: =L5*(1+Assumptions!$G$7) -> 131757.6 | P5: =J5*(1+Assumptions!$G$6) -> 195.31375 | Q5: =O5*P5 -> 25734071
B6: Industrial Assemblies | C6: 65000 | D6: 260 | E6: =C6*D6 -> 16900000 | F6: =C6*(1+Assumptions!$D$7) -> 66950 | G6: =D6*(1+Assumptions!$D$6) -> 267.8 | H6: =F6*G6 -> 17929210 | I6: =C6*(1+Assumptions!$E$6) -> 66625 | J6: =D6*(1+Assumptions!$E$6) -> 266.5 | K6: =I6*J6 -> 17755562 | L6: =I6*(1+Assumptions!$F$7) -> 69290 | M6: =G6*(1+Assumptions!$F$6) -> 275.834 | N6: =L6*M6 -> 19112538 | O6: =L6*(1+Assumptions!$G$7) -> 71368.7 | P6: =J6*(1+Assumptions!$G$6) -> 274.495 | Q6: =O6*P6 -> 19590351
B7: Automotive Components | C7: 62000 | D7: 175 | E7: =C7*D7 -> 10850000 | F7: =C7*(1+Assumptions!$D$7) -> 63860 | G7: =D7*(1+Assumptions!$D$6) -> 180.25 | H7: =F7*G7 -> 11510765 | I7: =C7*(1+Assumptions!$E$6) -> 63550 | J7: =D7*(1+Assumptions!$E$6) -> 179.375 | K7: =I7*J7 -> 11399281 | L7: =I7*(1+Assumptions!$F$7) -> 66092 | M7: =G7*(1+Assumptions!$F$6) -> 185.6575 | N7: =L7*M7 -> 12270475 | O7: =L7*(1+Assumptions!$G$7) -> 68074.76 | P7: =J7*(1+Assumptions!$G$6) -> 184.75625 | Q7: =O7*P7 -> 12577237
B8: Total | C8: =SUM(C5:C7) -> 247000 | E8: =SUM(E5:E7) -> 49950000 | F8: =SUM(F5:F7) -> 254410 | H8: =SUM(H5:H7) -> 52991955 | I8: =SUM(I5:I7) -> 253175 | K8: =SUM(K5:K7) -> 52478719 | L8: =SUM(L5:L7) -> 263302 | N8: =SUM(N5:N7) -> 56489424 | O8: =SUM(O5:O7) -> 271201.06 | Q8: =SUM(Q5:Q7) -> 57901660

Sheet Production_Model
B1: MidWest Precision Components, Inc.
B2: Production model
B4: Product | C4: 2025A Units Sold | D4: 2025A Scrap% | E4: 2025A Yield% | F4: 2025A Production | G4: 2026 Budget Production | H4: 2026 Forecast Production | I4: 2027 Plan Production | J4: 2028 Plan Production
B5: Precision Components | C5: 120000 | D5: =Assumptions!$C$9 -> 0.025 | E5: =1-D5 -> 0.975 | F5: =C5/E5 -> 123076.92 | G5: =C5*(1+Assumptions!$D$7)/(1-Assumptions!$D$9) -> 126639.34 | H5: =G5*(1+Assumptions!$E$7)/(1-Assumptions!$E$9) -> 133270.36 | I5: =H5*(1+Assumptions!$F$7)/(1-Assumptions!$F$9) -> 141864.04 | J5: =I5*(1+Assumptions!$G$7)/(1-Assumptions!$G$9) -> 149406.92
B6: Industrial Assemblies | C6: 65000 | D6: =Assumptions!$C$9 -> 0.025 | E6: =1-D6 -> 0.975 | F6: =C6/E6 -> 66666.667 | G6: =C6*(1+Assumptions!$D$7)/(1-Assumptions!$D$9) -> 68596.311 | H6: =G6*(1+Assumptions!$E$7)/(1-Assumptions!$E$9) -> 72188.11 | I6: =H6*(1+Assumptions!$F$7)/(1-Assumptions!$F$9) -> 76843.024 | J6: =I6*(1+Assumptions!$G$7)/(1-Assumptions!$G$9) -> 80928.747
B7: Automotive Components | C7: 62000 | D7: =Assumptions!$C$9 -> 0.025 | E7: =1-D7 -> 0.975 | F7: =C7/E7 -> 63589.744 | G7: =C7*(1+Assumptions!$D$7)/(1-Assumptions!$D$9) -> 65430.328 | H7: =G7*(1+Assumptions!$E$7)/(1-Assumptions!$E$9) -> 68856.351 | I7: =H7*(1+Assumptions!$F$7)/(1-Assumptions!$F$9) -> 73296.423 | J7: =I7*(1+Assumptions!$G$7)/(1-Assumptions!$G$9) -> 77193.574
F8: =SUM(F5:F7) -> 253333.33 | G8: =SUM(G5:G7) -> 260665.98 | H8: =SUM(H5:H7) -> 274314.82 | I8: =SUM(I5:I7) -> 292003.49 | J8: =SUM(J5:J7) -> 307529.24

Sheet Sourcing_Model
A1: MidWest Precision Components, Inc.
A2: Sourcing Model
A4: Growth Rate | B4: =3% -> 0.03
A5: Supplier price inflation | B5: 0.04
A6: Local currency price increase | B6: 0.035
A8: Material | B8: Suppiler Region | C8: Currency | D8: 2025A Quantity | E8: 2025A Unit Cost LC | F8: 2025A USD Spend | G8: 2026 Quantity | H8: 2026 Unit Cost LC | I8: 2026 FX | J8: 2026 USD Spend | K8: 2026F Quantity | L8: 2026F Unit Cost LC | M8: 2026F FX | N8: 2026F USD Spend | O8: 2027 Quantity | P8: 2027 Unit Cost LC | Q8: 2027 FX | R8: 2027 USD Spend | S8: 2028 Quantity | T8: 2028 Unit Cost LC | U8: 2028 FX | V8: 2028 USD Spend
A9: Steel & Metals | B9: Domestic | C9: USD | D9: 120000 | E9: 0.75 | F9: =D9*E9 -> 90000 | G9: =D9*(1+3%) -> 123600 | H9: =E9*(1+4%) -> 0.78 | I9: 1 | J9: =G9*H9*I9 -> 96408 | K9: =D9*(1+Assumptions!$E$7) -> 123000 | L9: =E9*(1+$B$5) -> 0.78 | M9: 1 | N9: =M9*L9*K9 -> 95940 | O9: =G9*(1+4%) -> 128544 | P9: =H9*1.035 -> 0.8073 | Q9: =I9 -> 1 | R9: =O9*P9*Q9 -> 103773.57 | S9: =O9*(1+3%) -> 132400.32 | T9: =P9*1.03 -> 0.831519 | U9: =1 -> 1 | V9: =S9*T9*U9 -> 110093.38
A10: Electronic Components | B10: Europe | C10: EUR | D10: 70000 | E10: 5.2 | F10: =D10*E10*FX_Assumptions!D5 -> 393120 | G10: =D10*(1+3%) -> 72100 | H10: =E10*(1+4%) -> 5.408 | I10: =FX_Assumptions!$F5 -> 1.09 | J10: =G10*H10*I10 -> 425009.31 | K10: =D10*(1+Assumptions!$E$7) -> 71750 | L10: =E10*(1+$B$5) -> 5.408 | M10: =FX_Assumptions!F6 -> 0.139 | N10: =M10*L10*K10 -> 53935.336 | O10: =G10*(1+4%) -> 74984 | P10: =H10*1.035 -> 5.59728 | Q10: =FX_Assumptions!$G5 -> 1.11 | R10: =O10*P10*Q10 -> 465874.15 | S10: =O10*(1+3%) -> 77233.52 | T10: =P10*1.03 -> 5.7651984 | U10: =FX_Assumptions!$H5 -> 1.12 | V10: =S10*T10*U10 -> 498698.55
A11: Specialty Inputs | B11: China | C11: CNY | D11: 180000 | E11: 16.5 | F11: =D11*E11*FX_Assumptions!D6 -> 409860 | G11: =D11*(1+3%) -> 185400 | H11: =E11*(1+4%) -> 17.16 | I11: =FX_Assumptions!$F6 -> 0.139 | J11: =G11*H11*I11 -> 442223.5 | K11: =D11*(1+Assumptions!$E$7) -> 184500 | L11: =E11*(1+$B$5) -> 17.16 | M11: 0 | N11: =M11*L11*K11 -> 0 | O11: =G11*(1+4%) -> 192816 | P11: =H11*1.035 -> 17.7606 | Q11: =FX_Assumptions!$G6 -> 0.142 | R11: =O11*P11*Q11 -> 486282.95 | S11: =O11*(1+3%) -> 198600.48 | T11: =P11*1.03 -> 18.293418 | U11: =FX_Assumptions!$H6 -> 0.145 | V11: =S11*T11*U11 -> 526796.83
A12: Total Material Spend | F12: =SUM(F9:F11) -> 892980 | J12: =SUM(J9:J11) -> 963640.81 | N12: =SUM(N9:N11) -> 149875.34 | R12: =SUM(R9:R11) -> 1055930.7 | V12: =SUM(V9:V11) -> 1135588.8
A15: International Sourcing exposure
A16: Metric | B16: 2025A | C16: 2026 | D16: 2027 | E16: 2028
A17: Total Material Spend | B17: =F12 -> 892980 | C17: =J12 -> 963640.81 | D17: =R12 -> 1055930.7 | E17: =V12 -> 1135588.8
A18: International Material Spend | B18: =F10+F11 -> 802980 | C18: =J10+J11 -> 867232.81 | D18: =R10+R11 -> 952157.11 | E18: =V11+V10 -> 1025495.4
A19: International % of Spend | B19: =B18/B17 -> 0.89921387 | C19: =C18/C17 -> 0.89995442 | D19: =D18/D17 -> 0.90172312 | E19: =E18/E17 -> 0.90305172
A20: EUR exposure | B20: =F10/F12 -> 0.44023382 | C20: =J10/C17 -> 0.44104537 | D20: =R10/R12 -> 0.44119767 | E20: =V10/V12 -> 0.43915418
A21: CNY exposure | B21: =F11/F12 -> 0.45898004 | C21: =J11/C18 -> 0.50992478 | D21: =R11/R12 -> 0.46052545 | E21: =V11/V12 -> 0.46389754

Sheet Direct_Labor
A1: MidWest Precision Components, Inc.
A2: Direct labour Cost
A4: Product | B4: 2025A Production Units | C4: Labor Hr/Unit | D4: 2025A Labor Hours | E4: 2025A Hourly Rate | F4: 2025A Direct Labor Cost | G4: 2026 Budget Hours | H4: 2026 Forecast Hours | I4: 2027 Plan Hours | J4: 2028 Plan Hours | K4: 2026 Hourly Rate | L4: 2026 Forecast Labor Cost | M4: 2026 Budget labor Cost | N4: 2027 Hourly Rate | O4: 2027 Labor Cost | P4: 2028 Hourly Rate | Q4: 2028 Labor Cost
A5: Precision Components | B5: =Production_Model!F5 -> 123076.92 | C5: 0.35 | D5: =C5*B5 -> 43076.923 | E5: 28 | F5: =E5*D5 -> 1206153.8 | G5: =C5*Production_Model!G5 -> 44323.77 | H5: =C5*Production_Model!H5 -> 46644.625 | I5: =Production_Model!I5*Direct_Labor!C5 -> 49652.416 | J5: =Production_Model!J5*Direct_Labor!C5 -> 52292.421 | K5: =E5*(1+Assumptions!D$10) -> 29.12 | L5: =H5*K5 -> 1358291.5 | M5: =K5*G5 -> 1290708.2 | N5: =K5*(1+Assumptions!F$10) -> 30.1392 | O5: =I5*N5 -> 1496484.1 | P5: =N5*(1+Assumptions!G$10) -> 31.194072 | Q5: =J5*P5 -> 1631213.6
A6: Industrial Assemblies | B6: =Production_Model!F6 -> 66666.667 | C6: 0.6 | D6: =C6*B6 -> 40000 | E6: 30 | F6: =E6*D6 -> 1200000 | G6: =C6*Production_Model!G6 -> 41157.787 | H6: =C6*Production_Model!H6 -> 43312.866 | I6: =Production_Model!I6*Direct_Labor!C6 -> 46105.814 | J6: =Production_Model!J6*Direct_Labor!C6 -> 48557.248 | K6: =E6*(1+Assumptions!D$10) -> 31.2 | L6: =H6*K6 -> 1351361.4 | M6: =K6*G6 -> 1284123 | N6: =K6*(1+Assumptions!F$10) -> 32.292 | O6: =I6*N6 -> 1488849 | P6: =N6*(1+Assumptions!G$10) -> 33.42222 | Q6: =J6*P6 -> 1622891
A7: Automotive Components | B7: =Production_Model!F7 -> 63589.744 | C7: 0.45 | D7: =C7*B7 -> 28615.385 | E7: 29 | F7: =E7*D7 -> 829846.15 | G7: =C7*Production_Model!G7 -> 29443.648 | H7: =C7*Production_Model!H7 -> 30985.358 | I7: =Production_Model!I7*Direct_Labor!C7 -> 32983.39 | J7: =Production_Model!J7*Direct_Labor!C7 -> 34737.108 | K7: =E7*(1+Assumptions!D$10) -> 30.16 | L7: =H7*K7 -> 934518.4 | M7: =K7*G7 -> 888020.41 | N7: =K7*(1+Assumptions!F$10) -> 31.2156 | O7: =I7*N7 -> 1029596.3 | P7: =N7*(1+Assumptions!G$10) -> 32.308146 | Q7: =J7*P7 -> 1122291.6
A8: TOTAL | D8: =SUM(D5:D7) -> 111692.31 | F8: =SUM(F5:F7) -> 3236000 | H8: =SUM(H5:H7) -> 120942.85 | L8: =SUM(L5:L7) -> 3644171.3 | M8: =SUM(M5:M7) -> 3462851.6 | O8: =SUM(O5:O7) -> 4014929.4 | Q8: =SUM(Q5:Q7) -> 4376396.2

Sheet Manufacturing_OH
A1: MidWest Precision Components, Inc.
A2: Manufacturing OH
A4: Cost Category | B4: Cost Type | C4: 2025A | D4: 2026 Budget | E4: 2026 Forecast | F4: 2027 Plan | G4: 2028 Plan | H4: Driver | I4: Notes
A5: Factory Utilities | B5: Variable | C5: 750000 | D5: =C5*Production_Model!G8/Production_Model!F8 -> 771708.5 | E5: =C5*(Production_Model!$H$8/Production_Model!$F$8) -> 812116.24 | F5: =E5*(Production_Model!$I$8/Production_Model!$H$8) -> 864484.02 | G5: =F5*(Production_Model!$J$8/Production_Model!$I$8) -> 910448.41 | H5: Production | I5: Assumed 3% Contractual increase
A6: Maintenance | B6: Variable | C6: 600000 | D6: =C6*(Production_Model!G8/Production_Model!F8) -> 617366.8 | E6: =C6*(Production_Model!$H$8/Production_Model!$F$8) -> 649692.99 | F6: =E6*(Production_Model!$I$8/Production_Model!$H$8) -> 691587.22 | G6: =F6*(Production_Model!$J$8/Production_Model!$I$8) -> 728358.73 | H6: Production
A7: Indirect Labor | B7: Fixed | C7: 1050000 | D7: =C7*(1+Assumptions!D10) -> 1092000 | E7: =C7*(1+Assumptions!D10) -> 1092000 | F7: =E$7*(1+Assumptions!F$10) -> 1130220 | G7: =F$7*(1+Assumptions!G$10) -> 1169777.7 | H7: Head Count
A8: Factory Rent | B8: Fixed | C8: 650000 | D8: =$C$8*(1+3%) -> 669500 | E8: =$C$8*(1+3%) -> 669500 | F8: =E8*(1+3%) -> 689585 | G8: =F8*(1+3%) -> 710272.55 | H8: Contract
A9: Factory Supplies | B9: Variable | C9: 350000 | D9: =C9*(Production_Model!G8/Production_Model!F8) -> 360130.64 | E9: =C9*(Production_Model!$H$8/Production_Model!$F$8) -> 378987.58 | F9: =E9*(Production_Model!$I$8/Production_Model!$H$8) -> 403425.88 | G9: =F9*(Production_Model!$J$8/Production_Model!$I$8) -> 424875.92 | H9: Production
A10: Total Manufacturing overhead | C10: =SUM(C5:C9) -> 3400000 | D10: =SUM(D5:D9) -> 3510705.9 | E10: =SUM(E5:E9) -> 3602296.8 | F10: =SUM(F5:F9) -> 3779302.1 | G10: =SUM(G5:G9) -> 3943733.3
A12: Metric
A13: Available production Capacity | C13: 280000 | D13: 290000 | E13: 290000 | F13: 310000 | G13: 330000
A14: Planned Prduction | C14: =Production_Model!F8 -> 253333.33 | D14: =Production_Model!G8 -> 260665.98 | E14: =Production_Model!H8 -> 274314.82 | F14: =Production_Model!I8 -> 292003.49 | G14: =Production_Model!J8 -> 307529.24
A15: Capacity Utilization | C15: =C14/C13 -> 0.9047619 | D15: =D14/D13 -> 0.89884822 | E15: =E14/E13 -> 0.94591317 | F15: =F14/F13 -> 0.94194675 | G15: =G14/G13 -> 0.93190679

Sheet Headcount
A1: MidWest Precision Components, Inc.
A2: Headcount
A5: Department | B5: 2025A HC | C5: 2026 Budget HC | D5: 2026 Forecast HC | E5: 2027 Plan HC | F5: 2028 Plan HC | G5: 2025 Avg Slry | H5: 2026 Avg Slry | I5: 2027 Avg Slry | J5: 2028 Avg Slry | K5: 2025 Payroll | L5: 2026 Payroll | M5: 2026 Forecast Payroll | N5: 2027 Payroll | O5: 2028 Payroll
A6: Finance | B6: 8 | C6: 9 | D6: 9 | E6: 9 | F6: 10 | G6: 85000 | H6: =G6*(1+Assumptions!D$10) -> 88400 | I6: =H6*(1+Assumptions!F$10) -> 91494 | J6: =I6*(1+Assumptions!G$10) -> 94696.29 | K6: =G6*B6 -> 680000 | L6: =H6*C6 -> 795600 | M6: =H6*D6 -> 795600 | N6: =I6*E6 -> 823446 | O6: =J6*F6 -> 946962.9
A7: Sales & Marketing | B7: 12 | C7: 13 | D7: 13 | E7: 14 | F7: 15 | G7: 78000 | H7: =G7*(1+Assumptions!D$10) -> 81120 | I7: =H7*(1+Assumptions!F$10) -> 83959.2 | J7: =I7*(1+Assumptions!G$10) -> 86897.772 | K7: =G7*B7 -> 936000 | L7: =H7*C7 -> 1054560 | M7: =H7*D7 -> 1054560 | N7: =I7*E7 -> 1175428.8 | O7: =J7*F7 -> 1303466.6
A8: Operations | B8: 18 | C8: 19 | D8: 20 | E8: 21 | F8: 22 | G8: 72000 | H8: =G8*(1+Assumptions!D$10) -> 74880 | I8: =H8*(1+Assumptions!F$10) -> 77500.8 | J8: =I8*(1+Assumptions!G$10) -> 80213.328 | K8: =G8*B8 -> 1296000 | L8: =H8*C8 -> 1422720 | M8: =H8*D8 -> 1497600 | N8: =I8*E8 -> 1627516.8 | O8: =J8*F8 -> 1764693.2
A9: Engineering | B9: 10 | C9: 11 | D9: 11 | E9: 12 | F9: 13 | G9: 95000 | H9: =G9*(1+Assumptions!D$10) -> 98800 | I9: =H9*(1+Assumptions!F$10) -> 102258 | J9: =I9*(1+Assumptions!G$10) -> 105837.03 | K9: =G9*B9 -> 950000 | L9: =H9*C9 -> 1086800 | M9: =H9*D9 -> 1086800 | N9: =I9*E9 -> 1227096 | O9: =J9*F9 -> 1375881.4
A10: HR & Administration | B10: 7 | C10: 7 | D10: 7 | E10: 8 | F10: 8 | G10: 68000 | H10: =G10*(1+Assumptions!D$10) -> 70720 | I10: =H10*(1+Assumptions!F$10) -> 73195.2 | J10: =I10*(1+Assumptions!G$10) -> 75757.032 | K10: =G10*B10 -> 476000 | L10: =H10*C10 -> 495040 | M10: =H10*D10 -> 495040 | N10: =I10*E10 -> 585561.6 | O10: =J10*F10 -> 606056.26
A11: IT | B11: 5 | C11: 6 | D11: 6 | E11: 6 | F11: 7 | G11: 88000 | H11: =G11*(1+Assumptions!D$10) -> 91520 | I11: =H11*(1+Assumptions!F$10) -> 94723.2 | J11: =I11*(1+Assumptions!G$10) -> 98038.512 | K11: =G11*B11 -> 440000 | L11: =H11*C11 -> 549120 | M11: =H11*D11 -> 549120 | N11: =I11*E11 -> 568339.2 | O11: =J11*F11 -> 686269.58
A12: Total | B12: =SUM(B6:B11) -> 60 | C12: =SUM(C6:C11) -> 65 | D12: =SUM(D6:D11) -> 66 | E12: =SUM(E6:E11) -> 70 | F12: =SUM(F6:F11) -> 75 | G12: =SUM(G6:G11) -> 486000 | H12: =SUM(H6:H11) -> 505440 | I12: =SUM(I6:I11) -> 523130.4 | ... O12: =SUM(O6:O11) -> 6683329.9

Sheet OpEx
A1: MidWest Precision Components, Inc.
A2: Operating Expense
A4: Expense Category | B4: 2025A | C4: 2026 Budget | D4: 2026 Forecast | E4: 2027 Plan | F4: 2028 Plan | G4: Driver
A5: Sales & Marketing | B5: 900000 | C5: =B5*(Revenue_Model!$H$5/Revenue_Model!$E$5) -> 954810 | D5: =B5*(Revenue_Model!$K$5/Revenue_Model!$E$5) -> 945562.5 | E5: =$B5*(Revenue_Model!$N$5/Revenue_Model!$E$5) -> 1017827.5 | F5: =$B5*(Revenue_Model!$Q$5/Revenue_Model!$E$5) -> 1043273.1 | G5: Revenue
A6: Travel & Entertainment | B6: 300000 | C6: =B6*(Revenue_Model!$H$5/Revenue_Model!$E$5) -> 318270 | D6: =B6*(Revenue_Model!$K$5/Revenue_Model!$E$5) -> 315187.5 | E6: =$B6*(Revenue_Model!$N$5/Revenue_Model!$E$5) -> 339275.82 | F6: =$B6*(Revenue_Model!$Q$5/Revenue_Model!$E$5) -> 347757.72 | G6: Revenue
A7: Professional Services | B7: 400000 | C7: =B7*(Revenue_Model!$H$5/Revenue_Model!$E$5) -> 424360 | D7: =B7*(Revenue_Model!$K$5/Revenue_Model!$E$5) -> 420250 | E7: =$B7*(Revenue_Model!$N$5/Revenue_Model!$E$5) -> 452367.76 | F7: =$B7*(Revenue_Model!$Q$5/Revenue_Model!$E$5) -> 463676.95 | G7: Revenue
A8: Software & Technology | B8: 350000 | C8: =B8*(Headcount!$C$12/Headcount!$B$12) -> 379166.67 | D8: =B8*(Headcount!$D$12/Headcount!$B$12) -> 385000 | E8: =B8*(Headcount!$E$12/Headcount!$B$12) -> 408333.33 | F8: =B8*(Headcount!$F$12/Headcount!$B$12) -> 437500 | G8: Headcount
A9: Insurance | B9: 250000 | C9: =B9*(Revenue_Model!$H$5/Revenue_Model!$E$5) -> 265225 | D9: =B9*(Revenue_Model!$K$5/Revenue_Model!$E$5) -> 262656.25 | E9: =$B9*(Revenue_Model!$N$5/Revenue_Model!$E$5) -> 282729.85 | F9: =$B9*(Revenue_Model!$Q$5/Revenue_Model!$E$5) -> 289798.1 | G9: Revenue
A10: Office & Administration | B10: 220000 | C10: =B10*(Headcount!$C$12/Headcount!$B$12) -> 238333.33 | D10: =B10*(Headcount!$D$12/Headcount!$B$12) -> 242000 | E10: =B10*(Headcount!$E$12/Headcount!$B$12) -> 256666.67 | F10: =B10*(Headcount!$F$12/Headcount!$B$12) -> 275000 | G10: Headcount
A11: Other operating Expense | B11: 180000 | C11: =B11*(Revenue_Model!$H$5/Revenue_Model!$E$5) -> 190962 | D11: =B11*(Revenue_Model!$K$5/Revenue_Model!$E$5) -> 189112.5 | E11: =$B11*(Revenue_Model!$N$5/Revenue_Model!$E$5) -> 203565.49 | F11: =$B11*(Revenue_Model!$Q$5/Revenue_Model!$E$5) -> 208654.63 | G11: Revenue
A12: Expected Total | B12: =SUM(B5:B11) -> 2600000 | C12: =SUM(C5:C11) -> 2771127 | D12: =SUM(D5:D11) -> 2759768.7 | E12: =SUM(E5:E11) -> 2960766.4 | F12: =SUM(F5:F11) -> 3065660.5

Sheet CapEx
A1: MidWest Precision Components, Inc.
A2: Operating Expense
A4: CapEx Category | B4: 2025A | C4: 2026 Budget | D4: 2026 Forecast | E4: 2027 Plan | F4: 2028 Plan | G4: Driver | H4: Useful Life (in years) | I4: Notes
A5: Production Equipment | B5: 900000 | C5: =B5*(Production_Model!G8/Production_Model!F8) -> 926050.2 | D5: =$B5*(Production_Model!H$8/Production_Model!$F$8) -> 974539.49 | E5: =D5*(Production_Model!I8/Production_Model!H8) -> 1037380.8 | F5: =E5*(Production_Model!J8/Production_Model!I8) -> 1092538.1 | G5: Production | H5: 10 | I5: Maintence increases by 5%
A6: Facility Improvements | B6: 300000 | C6: 300000 | D6: 300000 | E6: 400000 | F6: 500000 | G6: Capacity | H6: 15
A7: Technology & Systems | B7: 200000 | C7: =$B7*(Headcount!C12/Headcount!B12) -> 216666.67 | D7: =$B7*(Headcount!$D12/Headcount!$C$12) -> 203076.92 | E7: =D7*(Headcount!E12/Headcount!D12) -> 215384.62 | F7: =E7*(Headcount!F12/Headcount!E12) -> 230769.23 | G7: Headcount | H7: 5
A8: Maintenance CapEx | B8: 350000 | C8: =$B8*(1+5%) -> 367500 | D8: =$B8*(1+5%) -> 367500 | E8: =$B8*(1+5%) -> 367500 | F8: =$B8*(1+5%) -> 367500 | G8: Existing Assets | H8: 7
A9: Capacity Expansion | B9: 0 | C9: 0 | D9: 0 | E9: 0 | F9: 2500000 | G9: Utlization | H9: 10
A10: Total CapEx | B10: =SUM(B5:B9) -> 1750000 | C10: =SUM(C5:C9) -> 1810216.9 | D10: =SUM(D5:D9) -> 1845116.4 | E10: =SUM(E5:E9) -> 2020265.4 | F10: =SUM(F5:F9) -> 4690807.3
A14: Metric | B14: 2025A | C14: 2026 Budget | D14: 2026 Forecast | E14: 2027 Plan | F14: 2028 Plan
A15: Total CapEx | B15: =B10 -> 1750000 | C15: =C10 -> 1810216.9 | D15: =D10 -> 1845116.4 | E15: =E10 -> 2020265.4 | F15: =F10 -> 4690807.3
A16: CapEx / Revenue | B16: =B10/Revenue_Model!E8 -> 0.035035035 | C16: =C10/Revenue_Model!H8 -> 0.034160221 | D16: =D10/Revenue_Model!K8 -> 0.035159327 | E16: =E10/Revenue_Model!N8 -> 0.035763605 | F16: =F10/Revenue_Model!Q8 -> 0.081013348
A17: Production Capacity | B17: =Production_Model!F8 -> 253333.33 | C17: =Production_Model!G8 -> 260665.98 | D17: =Production_Model!H8 -> 274314.82 | E17: =Production_Model!I8 -> 292003.49 | F17: =Production_Model!J8 -> 307529.24
A18: Capacity Utilization | B18: =Manufacturing_OH!C15 -> 0.9047619 | C18: =Manufacturing_OH!D15 -> 0.89884822 | D18: =Manufacturing_OH!E15 -> 0.94591317 | E18: =Manufacturing_OH!F15 -> 0.94194675 | F18: =Manufacturing_OH!G15 -> 0.93190679
A19: Capacity Expansion Required? | B19: =IF(AND(B14<>"2025A",B18>90%),"Yes","No") -> No | C19: =IF(AND(C14<>"2025A",C18>90%),"Yes","No") -> No | D19: =IF(AND(D14<>"2025A",D18>90%),"Yes","No") -> Yes | E19: =IF(AND(E14<>"2025A",E18>90%),"Yes","No") -> Yes | F19: =IF(AND(F14<>"2025A",F18>90%),"Yes","No") -> Yes
A22: Depreciation Schedule (Straight-Line, Cumulative Vintages)
A24: Category | B24: 2025A | C24: 2026 Budget | D24: 2026 Forecast | E24: 2027 Plan | F24: 2028 Plan
A25: Production Equipment | B25: =B5/H5 -> 90000 | C25: =B25+C5/H5 -> 182605.02 | D25: =B25+D5/H5 -> 187453.95 | E25: =D25+E5/H5 -> 291192.03 | F25: =E25+F5/H5 -> 400445.84
A26: Facility Improvements | B26: =B6/H6 -> 20000 | C26: =B26+C6/H6 -> 40000 | D26: =B26+D6/H6 -> 40000 | E26: =D26+E6/H6 -> 66666.667 | F26: =E26+F6/H6 -> 100000
A27: Technology & Systems | B27: =B7/H7 -> 40000 | C27: =B27+C7/H7 -> 83333.333 | D27: =B27+D7/H7 -> 80615.385 | E27: =D27+E7/H7 -> 123692.31 | F27: =E27+F7/H7 -> 169846.15
A28: Maintenance CapEx | B28: =B8/H8 -> 50000 | C28: =B28+C8/H8 -> 102500 | D28: =B28+D8/H8 -> 102500 | E28: =D28+E8/H8 -> 155000 | F28: =E28+F8/H8 -> 207500
A29: Capacity Expansion | B29: =B9/H9 -> 0 | C29: =B29+C9/H9 -> 0 | D29: =B29+D9/H9 -> 0 | E29: =D29+E9/H9 -> 0 | F29: =E29+F9/H9 -> 250000
A30: Total Depreciation & Amortization | B30: =SUM(B25:B29) -> 200000 | C30: =SUM(C25:C29) -> 408438.35 | D30: =SUM(D25:D29) -> 410569.33 | E30: =SUM(E25:E29) -> 636551.01 | F30: =SUM(F25:F29) -> 1127792

Sheet Working_Capital
A1: MidWest Precision Components, Inc.
A2: Working Capital Schedule
A4: Metric | B4: 2025A | C4: 2026 Budget | D4: 2026 Forecast | E4: 2027 Plan | F4: 2028 Plan
A5: Accounts Receivable | B5: =('P&L'!B5/365)*Assumptions!C12 -> 6568767.1 | C5: =('P&L'!C5/365)*Assumptions!D12 -> 6823621.6 | D5: =('P&L'!D5/365)*Assumptions!E12 -> 7045088.3 | E5: =('P&L'!E5/365)*Assumptions!F12 -> 7119215.1 | F5: =('P&L'!F5/365)*Assumptions!G12 -> 7138560.8
A6: Inventory | B6: =('P&L'!B6/365)*Assumptions!C13 -> 5854413.7 | C6: =('P&L'!C6/365)*Assumptions!D13 -> 5923484.3 | D6: =('P&L'!D6/365)*Assumptions!E13 -> 6349206.1 | E6: =('P&L'!E6/365)*Assumptions!F13 -> 6163537.8 | F6: =('P&L'!F6/365)*Assumptions!G13 -> 6013047.7
A7: Accounts Payable | B7: =('P&L'!B6/365)*Assumptions!C14 -> 3965893.2 | C7: =('P&L'!C6/365)*Assumptions!D14 -> 4245163.7 | D7: =('P&L'!D6/365)*Assumptions!E14 -> 4365079.2 | E7: =('P&L'!E6/365)*Assumptions!F14 -> 4492070 | F7: =('P&L'!F6/365)*Assumptions!G14 -> 4430666.7
A8: Net Working Capital | B8: =B5+B6-B7 -> 8457287.7 | C8: =C5+C6-C7 -> 8501942.2 | D8: =D5+D6-D7 -> 9029215.2 | E8: =E5+E6-E7 -> 8790683 | F8: =F5+F6-F7 -> 8720941.7
A9: Change in Net Working Capital | B9: 0 | C9: =C8-B8 -> 44654.479 | D9: =D8-B8 -> 571927.5 | E9: =E8-D8 -> -238532.2 | F9: =F8-E8 -> -69741.224
A11: Days Metrics (Memo)
A12: DSO (days) | B12: =Assumptions!C12 -> 48 | C12: =Assumptions!D12 -> 47 | D12: =Assumptions!E12 -> 49 | E12: =Assumptions!F12 -> 46 | F12: =Assumptions!G12 -> 45
A13: DIO (days) | B13: =Assumptions!C13 -> 62 | C13: =Assumptions!D13 -> 60 | D13: =Assumptions!E13 -> 64 | E13: =Assumptions!F13 -> 59 | F13: =Assumptions!G13 -> 57
A14: DPO (days) | B14: =Assumptions!C14 -> 42 | C14: =Assumptions!D14 -> 43 | D14: =Assumptions!E14 -> 44 | E14: =Assumptions!F14 -> 43 | F14: =Assumptions!G14 -> 42
A15: Cash Conversion Cycle (days) | B15: =B12+B13-B14 -> 68 | C15: =C12+C13-C14 -> 64 | D15: =D12+D13-D14 -> 69 | E15: =E12+E13-E14 -> 62 | F15: =F12+F13-F14 -> 60

Sheet P&L
A1: MidWest Precision Components, Inc.
A2: Consolidated Income Statement ($)
B4: 2025A | C4: 2026 Budget | D4: 2026 Forecast | E4: 2027 Plan | F4: 2028 Plan
A5: Revenue | B5: =Revenue_Model!E8 -> 49950000 | C5: =Revenue_Model!H8 -> 52991955 | D5: =Revenue_Model!K8 -> 52478719 | E5: =Revenue_Model!N8 -> 56489424 | F5: =Revenue_Model!Q8 -> 57901660
A6: Cost of Goods Sold (COGS) | B6: =B5*(1-Assumptions!C8) -> 34465500 | C6: =C5*(1-Assumptions!D8) -> 36034529 | D6: =D5*(1-Assumptions!E8) -> 36210316 | E6: =E5*(1-Assumptions!F8) -> 38130361 | F6: =F5*(1-Assumptions!G8) -> 38504604
A7: Gross Profit | B7: =B5-B6 -> 15484500 | C7: =C5-C6 -> 16957426 | D7: =D5-D6 -> 16268403 | E7: =E5-E6 -> 18359063 | F7: =F5-F6 -> 19397056
A8: Gross Margin % | B8: =B7/B5 -> 0.31 | C8: =C7/C5 -> 0.32 | D8: =D7/D5 -> 0.31 | E8: =E7/E5 -> 0.325 | F8: =F7/F5 -> 0.335
A9: SG&A - Operating Expenses | B9: =OpEx!B12 -> 2600000 | C9: =OpEx!C12 -> 2771127 | D9: =OpEx!D12 -> 2759768.7 | E9: =OpEx!E12 -> 2960766.4 | F9: =OpEx!F12 -> 3065660.5
A10: SG&A - Corporate Payroll | B10: =Headcount!K12 -> 4778000 | C10: =Headcount!L12 -> 5403840 | D10: =Headcount!M12 -> 5478720 | E10: =Headcount!N12 -> 6007388.4 | F10: =Headcount!O12 -> 6683329.9
A11: Total Operating Expenses | B11: =SUM(B9:B10) -> 7378000 | C11: =SUM(C9:C10) -> 8174967 | D11: =SUM(D9:D10) -> 8238488.8 | E11: =SUM(E9:E10) -> 8968154.8 | F11: =SUM(F9:F10) -> 9748990.5
A12: EBITDA | B12: =B7-B11 -> 8106500 | C12: =C7-C11 -> 8782458.6 | D12: =D7-D11 -> 8029914.1 | E12: =E7-E11 -> 9390908 | F12: =F7-F11 -> 9648065.5
A13: EBITDA Margin % | B13: =B12/B5 -> 0.16229229 | C13: =C12/C5 -> 0.16573192 | D13: =D12/D5 -> 0.15301277 | E13: =E12/E5 -> 0.16624188 | F13: =F12/F5 -> 0.16662848
A14: Depreciation & Amortization | B14: =CapEx!B30 -> 200000 | C14: =CapEx!C30 -> 408438.35 | D14: =CapEx!D30 -> 410569.33 | E14: =CapEx!E30 -> 636551.01 | F14: =CapEx!F30 -> 1127792
A15: EBIT (Operating Income) | B15: =B12-B14 -> 7906500 | C15: =C12-C14 -> 8374020.2 | D15: =D12-D14 -> 7619344.7 | E15: =E12-E14 -> 8754357 | F15: =F12-F14 -> 8520273.5
A16: EBIT Margin % | B16: =B15/B5 -> 0.15828829 | C16: =C15/C5 -> 0.15802437 | D16: =D15/D5 -> 0.14518923 | E16: =E15/E5 -> 0.15497338 | F16: =F15/F5 -> 0.14715077
A17: Interest Expense | B17: 0 | C17: 0 | D17: 0 | E17: 0 | F17: 0
A18: Earnings Before Tax | B18: =B15-B17 -> 7906500 | C18: =C15-C17 -> 8374020.2 | D18: =D15-D17 -> 7619344.7 | E18: =E15-E17 -> 8754357 | F18: =F15-F17 -> 8520273.5
A19: Income Tax Expense | B19: =B18*Assumptions!C16 -> 1976625 | C19: =C18*Assumptions!D16 -> 2093505.1 | D19: =D18*Assumptions!E16 -> 1904836.2 | E19: =E18*Assumptions!F16 -> 2188589.3 | F19: =F18*Assumptions!G16 -> 2130068.4
A20: Net Income | B20: =B18-B19 -> 5929875 | C20: =C18-C19 -> 6280515.2 | D20: =D18-D19 -> 5714508.5 | E20: =E18-E19 -> 6565767.8 | F20: =F18-F19 -> 6390205.1
A21: Net Margin % | B21: =B20/B5 -> 0.11871622 | C21: =C20/C5 -> 0.11851828 | D21: =D20/D5 -> 0.10889192 | E21: =E20/E5 -> 0.11623004 | F21: =F20/F5 -> 0.11036307
A23: Memo : Bottom-up Cost build (Reconciliation)
A24: Direct Labor Cost | B24: =Direct_Labor!F8 -> 3236000 | C24: =Direct_Labor!M8 -> 3462851.6 | D24: =Direct_Labor!L8 -> 3644171.3 | E24: =Direct_Labor!O8 -> 4014929.4 | F24: =Direct_Labor!Q8 -> 4376396.2
A25: Direct Materials Spend | B25: =Sourcing_Model!F12 -> 892980 | C25: =Sourcing_Model!J12 -> 963640.81 | D25: =Sourcing_Model!N12 -> 149875.34 | E25: =Sourcing_Model!R12 -> 1055930.7 | F25: =Sourcing_Model!V12 -> 1135588.8
A26: Manufacturing Overhead | B26: =Manufacturing_OH!C10 -> 3400000 | C26: =Manufacturing_OH!D10 -> 3510705.9 | D26: =Manufacturing_OH!E10 -> 3602296.8 | E26: =Manufacturing_OH!F10 -> 3779302.1 | F26: =Manufacturing_OH!G10 -> 3943733.3
A27: Total Bottom-Up Cost Build | B27: =SUM(B24:B26) -> 7528980 | C27: =SUM(C24:C26) -> 7937198.3 | D27: =SUM(D24:D26) -> 7396343.4 | E27: =SUM(E24:E26) -> 8850162.2 | F27: =SUM(F24:F26) -> 9455718.2
A28: Variance vs. Top-Down COGS | B28: =B27-B6 -> -26936520 | C28: =C27-C6 -> -28097331 | D28: =D27-D6 -> -28813972 | E28: =E27-E6 -> -29280199 | F28: =F27-F6 -> -29048885

Sheet Cash_Flow
A1: MidWest Precision Components, Inc.
A2: Statement of Cash Flows
B4: 2025A | C4: 2026 Budget | D4: 2026 Forecast | E4: 2027 Plan | F4: 2028 Plan
A5: Cash Flow from Operations
A6: Net Income | B6: ='P&L'!B20 -> 5929875 | C6: ='P&L'!C20 -> 6280515.2 | D6: ='P&L'!D20 -> 5714508.5 | E6: ='P&L'!E20 -> 6565767.8 | F6: ='P&L'!F20 -> 6390205.1
A7: + Depreciation & Amortization | B7: =CapEx!B30 -> 200000 | C7: =CapEx!C30 -> 408438.35 | D7: =CapEx!D30 -> 410569.33 | E7: =CapEx!E30 -> 636551.01 | F7: =CapEx!F30 -> 1127792
A8: - (Increase) / Decrease in NWC | B8: =Working_Capital!B9 -> 0 | C8: =-Working_Capital!C9 -> -44654.479 | D8: =-Working_Capital!D9 -> -571927.5 | E8: =-Working_Capital!E9 -> 238532.2 | F8: =-Working_Capital!F9 -> 69741.224
A9: Cash Flow from Operations (CFO) | B9: =SUM(B6:B8) -> 6129875 | C9: =SUM(C6:C8) -> 6644299.1 | D9: =SUM(D6:D8) -> 5553150.4 | E9: =SUM(E6:E8) -> 7440851 | F9: =SUM(F6:F8) -> 7587738.4
A11: Cash Flow from Investing
A12: CapEx | B12: =-CapEx!B10 -> -1750000 | C12: =-CapEx!C10 -> -1810216.9 | D12: =-CapEx!D10 -> -1845116.4 | E12: =-CapEx!E10 -> -2020265.4 | F12: =-CapEx!F10 -> -4690807.3
A13: Cash Flow from Investing (CFI) | B13: =B12 -> -1750000 | C13: =C12 -> -1810216.9 | D13: =D12 -> -1845116.4 | E13: =E12 -> -2020265.4 | F13: =F12 -> -4690807.3
A15: Cash Flow from Financing
A16: Debt / Dividends / Buybacks | B16: 0 | C16: 0 | D16: 0 | E16: 0 | F16: 0
A17: Cash Flow from Financing (CFF) | B17: =B16 -> 0 | C17: =C16 -> 0 | D17: =D16 -> 0 | E17: =E16 -> 0 | F17: =F16 -> 0
A19: Net Change in Cash | B19: =B17+B13+B9 -> 4379875 | C19: =C17+C13+C9 -> 4834082.2 | D19: =D17+D13+D9 -> 3708034 | E19: =E17+E13+E9 -> 5420585.5 | F19: =F17+F13+F9 -> 2896931
A20: Beginning Cash Balance | B20: 2000000 | C20: =B21 -> 6379875 | D20: =B21 -> 6379875 | E20: =D21 -> 10087909 | F20: =E21 -> 15508495
A21: Ending Cash Balance | B21: =B20+B19 -> 6379875 | C21: =C20+C19 -> 11213957 | D21: =D20+D19 -> 10087909 | E21: =E20+E19 -> 15508495 | F21: =F20+F19 -> 18405426

Sheet Budget_vs_Actual
A1: MidWest Precision Components, Inc.
A2: 2026 Budget vs. Forecast Variance Analysis
A4: Metric | B4: 2026 Budget | C4: 2026 Forecast | D4: $ Variance | E4: % Variance | F4: Fav / (Unfav)
A5: Revenue | B5: ='P&L'!C5 -> 52991955 | C5: ='P&L'!D5 -> 52478719 | D5: =C5-B5 -> -513236.25 | E5: =IFERROR(D5/B5,0) -> -0.009685173 | F5: =IF(D5>=0,"Favorable","Unfavorable") -> Unfavorable
A6: Cost of Goods Sold | B6: ='P&L'!C6 -> 36034529 | C6: ='P&L'!D6 -> 36210316 | D6: =C6-B6 -> 175786.54 | E6: =IFERROR(D6/B6,0) -> 0.0048782804 | F6: =IF(D6<=0,"Favorable","Unfavorable") -> Unfavorable
A7: Gross Profit | B7: ='P&L'!C7 -> 16957426 | C7: ='P&L'!D7 -> 16268403 | D7: =C7-B7 -> -689022.79 | E7: =IFERROR(D7/B7,0) -> -0.040632511 | F7: =IF(D7>=0,"Favorable","Unfavorable") -> Unfavorable
A8: Gross Margin % | B8: ='P&L'!C8 -> 0.32 | C8: ='P&L'!D8 -> 0.31 | D8: =C8-B8 -> -0.01 | E8: =IFERROR(D8/B8,0) -> -0.03125 | F8: =IF(D8>=0,"Favorable","Unfavorable") -> Unfavorable
A9: Total Operating Expenses | B9: ='P&L'!C11 -> 8174967 | C9: ='P&L'!D11 -> 8238488.8 | D9: =C9-B9 -> 63521.75 | E9: =IFERROR(D9/B9,0) -> 0.007770276 | F9: =IF(D9<=0,"Favorable","Unfavorable") -> Unfavorable
A10: EBITDA | B10: ='P&L'!C12 -> 8782458.6 | C10: ='P&L'!D12 -> 8029914.1 | D10: =C10-B10 -> -752544.54 | E10: =IFERROR(D10/B10,0) -> -0.085687229 | F10: =IF(D10>=0,"Favorable","Unfavorable") -> Unfavorable
A11: EBIT (Operating Income) | B11: ='P&L'!C15 -> 8374020.2 | C11: ='P&L'!D15 -> 7619344.7 | D11: =C11-B11 -> -754675.52 | E11: =IFERROR(D11/B11,0) -> -0.090121052 | F11: =IF(D11>=0,"Favorable","Unfavorable") -> Unfavorable
A12: Net Income | B12: ='P&L'!C20 -> 6280515.2 | C12: ='P&L'!D20 -> 5714508.5 | D12: =C12-B12 -> -566006.64 | E12: =IFERROR(D12/B12,0) -> -0.090121052 | F12: =IF(D12>=0,"Favorable","Unfavorable") -> Unfavorable

Sheet Forecast
A1: MidWest Precision Components, Inc.
A2: 4-Year Forecast Summary (Best-Estimate Path: 2025A -> 2026 Forecast -> 2027 Plan -> 2028 Plan)
A4: Metric | B4: 2025A | C4: 2026 Forecast | D4: 2027 Plan | E4: 2028 Plan
A5: Revenue | B5: ='P&L'!B5 -> 49950000 | C5: ='P&L'!D5 -> 52478719 | D5: ='P&L'!E5 -> 56489424 | E5: ='P&L'!F5 -> 57901660
A6: Revenue Growth % YoY | B6: - | C6: =C5/B5-1 -> 0.050625 | D6: =D5/C5-1 -> 0.076425366 | E6: =E5/D5-1 -> 0.025
A7: Gross Margin % | B7: ='P&L'!B8 -> 0.31 | C7: ='P&L'!D8 -> 0.31 | D7: ='P&L'!E8 -> 0.325 | E7: ='P&L'!F8 -> 0.335
A8: EBITDA Margin % | B8: ='P&L'!B13 -> 0.16229229 | C8: ='P&L'!C13 -> 0.16573192 | D8: ='P&L'!D13 -> 0.15301277 | E8: ='P&L'!E13 -> 0.16624188
A9: EBIT Margin % | B9: ='P&L'!B16 -> 0.15828829 | C9: ='P&L'!D16 -> 0.14518923 | D9: ='P&L'!E16 -> 0.15497338 | E9: ='P&L'!F16 -> 0.14715077
A10: Net Margin % | B10: ='P&L'!B21 -> 0.11871622 | C10: ='P&L'!D21 -> 0.10889192 | D10: ='P&L'!E21 -> 0.11623004 | E10: ='P&L'!F21 -> 0.11036307
A11: Net Income | B11: ='P&L'!B20 -> 5929875 | C11: ='P&L'!D20 -> 5714508.5 | D11: ='P&L'!E20 -> 6565767.8 | E11: ='P&L'!F20 -> 6390205.1
A12: Free Cash Flow (CFO - CapEx) | B12: =Cash_Flow!B9+Cash_Flow!B12 -> 4379875 | C12: =Cash_Flow!D9+Cash_Flow!D12 -> 3708034 | D12: =Cash_Flow!E9+Cash_Flow!E12 -> 5420585.5 | E12: =Cash_Flow!F9+Cash_Flow!F12 -> 2896931
A13: Ending Cash Balance | B13: =Cash_Flow!B21 -> 6379875 | C13: =Cash_Flow!D21 -> 10087909 | D13: =Cash_Flow!E21 -> 15508495 | E13: =Cash_Flow!F21 -> 18405426

Sheet Scenario_Analysis
A1: MidWest Precision Components, Inc.
A2: 2026 Scenario Analysis: Base / Upside / Downside
A4: Scenario | B4: Rev. Growth Delta (pp) | C4: Gross Margin Delta (pp) | D4: Revenue | E4: Gross Profit | F4: Gross Margin % | G4: EBIT | H4: Net Income
A5: Downside | B5: -0.03 | C5: -0.015 | D5: ='P&L'!$B$5*(1+Assumptions!$E$5+Scenario_Analysis!B5) -> 50949000 | E5: =D5*F5 -> 15029955 | F5: =Assumptions!$E$8+Scenario_Analysis!C5 -> 0.295 | G5: =E5-'P&L'!$D$11-'P&L'!$D$14 -> 6380896.9 | H5: =G5*(1-Assumptions!$E$16) -> 4785672.7
A6: Base | B6: 0 | C6: 0 | D6: ='P&L'!$B$5*(1+Assumptions!$E$5+Scenario_Analysis!B6) -> 52447500 | E6: =D6*F6 -> 16258725 | F6: =Assumptions!$E$8+Scenario_Analysis!C6 -> 0.31 | G6: =E6-'P&L'!$D$11-'P&L'!$D$14 -> 7609666.9 | H6: =G6*(1-Assumptions!$E$16) -> 5707250.2
A7: Upside | B7: 0.02 | C7: 0.01 | D7: ='P&L'!$B$5*(1+Assumptions!$E$5+Scenario_Analysis!B7) -> 53446500 | E7: =D7*F7 -> 17102880 | F7: =Assumptions!$E$8+Scenario_Analysis!C7 -> 0.32 | G7: =E7-'P&L'!$D$11-'P&L'!$D$14 -> 8453821.9 | H7: =G7*(1-Assumptions!$E$16) -> 6340366.4
A9: Selected Scenario (per Control Panel) | B9: ='Control Panel'!C4 -> Upside
B10: Revenue | C10: Gross Profit | D10: Gross Margin % | E10: EBIT | F10: Net Income
B11: =INDEX(D5:D7,MATCH($B$9,$A$5:$A$7,0)) -> 53446500 | C11: =INDEX(E5:E7,MATCH($B$9,$A$5:$A$7,0)) -> 17102880 | D11: =INDEX(F5:F7,MATCH($B$9,$A$5:$A$7,0)) -> 0.32 | E11: =INDEX(G5:G7,MATCH($B$9,$A$5:$A$7,0)) -> 8453821.9 | F11: =INDEX(H5:H7,MATCH($B$9,$A$5:$A$7,0)) -> 6340366.4

Sheet Variance_Drivers
A1: MidWest Precision Components, Inc.
A2: Revenue Variance Bridge: 2026 Budget vs. 2026 Forecast
A4: Product | B4: 2026 Budget Revenue | C4: Volume Variance | D4: Price Variance | E4: 2026 Forecast Revenue
A5: =[1]Revenue_Model!A3 -> Precision Components | B5: =Revenue_Model!H5 -> 23551980 | C5: =(Revenue_Model!I5-Revenue_Model!F5)*Revenue_Model!G5 -> -114330 | D5: =(Revenue_Model!J5-Revenue_Model!G5)*Revenue_Model!I5 -> -113775 | E5: =Revenue_Model!K5 -> 23323875
A6: =[1]Revenue_Model!A4 -> Industrial Assemblies | B6: =Revenue_Model!H6 -> 17929210 | C6: =(Revenue_Model!I6-Revenue_Model!F6)*Revenue_Model!G6 -> -87035 | D6: =(Revenue_Model!J6-Revenue_Model!G6)*Revenue_Model!I6 -> -86612.5 | E6: =Revenue_Model!K6 -> 17755562
A7: =[1]Revenue_Model!A5 -> Automotive Components | B7: =Revenue_Model!H7 -> 11510765 | C7: =(Revenue_Model!I7-Revenue_Model!F7)*Revenue_Model!G7 -> -55877.5 | D7: =(Revenue_Model!J7-Revenue_Model!G7)*Revenue_Model!I7 -> -55606.25 | E7: =Revenue_Model!K7 -> 11399281
A8: Total | B8: =SUM(B5:B7) -> 52991955 | C8: =SUM(C5:C7) -> -257242.5 | D8: =SUM(D5:D7) -> -255993.75 | E8: =SUM(E5:E7) -> 52478719
A10: BRIDGE CHECK | B10: =B8+C8+D8 -> 52478719 | C10: Forecast Revenue | D10: =E8 -> 52478719 | E10: =IF(ROUND(B10-D10,0)=0,"Ties Out","CHECK") -> Ties Out

Sheet Management_Dashboard
A1: MidWest Precision Components, Inc.
A2: Management Dashboard
A4: =CONCATENATE("Scenario: ",'Control Panel'!C4,"| Model Version: ",'Control Panel'!C11) -> Scenario: Upside| Model Version: v1.0
A6: KPI | B6: 2025A | C6: 2026 Budget | D6: 2026 Forecast | E6: 2027 Plan | F6: 2028 Plan
A7: Revenue ($) | B7: ='P&L'!B5 -> 49950000 | C7: ='P&L'!C5 -> 52991955 | D7: ='P&L'!D5 -> 52478719 | E7: ='P&L'!E5 -> 56489424 | F7: ='P&L'!F5 -> 57901660
A8: Gross Margin % | B8: ='P&L'!B8 -> 0.31 | C8: ='P&L'!C8 -> 0.32 | D8: ='P&L'!D8 -> 0.31 | E8: ='P&L'!E8 -> 0.325 | F8: ='P&L'!F8 -> 0.335
A9: EBITDA Margin % | B9: ='P&L'!B13 -> 0.16229229 | C9: ='P&L'!C13 -> 0.16573192 | D9: ='P&L'!D13 -> 0.15301277 | E9: ='P&L'!E13 -> 0.16624188 | F9: ='P&L'!F13 -> 0.16662848
A10: Net Margin % | B10: ='P&L'!B21 -> 0.11871622 | C10: ='P&L'!C21 -> 0.11851828 | D10: ='P&L'!D21 -> 0.10889192 | E10: ='P&L'!E21 -> 0.11623004 | F10: ='P&L'!F21 -> 0.11036307
A11: Net Income ($) | B11: ='P&L'!B20 -> 5929875 | C11: ='P&L'!C20 -> 6280515.2 | D11: ='P&L'!D20 -> 5714508.5 | E11: ='P&L'!E20 -> 6565767.8 | F11: ='P&L'!F20 -> 6390205.1
A12: CapEx % of Revenue | B12: =CapEx!B16 -> 0.035035035 | C12: =CapEx!C16 -> 0.034160221 | D12: =CapEx!D16 -> 0.035159327 | E12: =CapEx!E16 -> 0.035763605 | F12: =CapEx!F16 -> 0.081013348
A13: Capacity Utilization | B13: =CapEx!B18 -> 0.9047619 | C13: =CapEx!C18 -> 0.89884822 | D13: =CapEx!D18 -> 0.94591317 | E13: =CapEx!E18 -> 0.94194675 | F13: =CapEx!F18 -> 0.93190679
A14: Cash Conversion Cycle (days) | B14: =Working_Capital!B15 -> 68 | C14: =Working_Capital!C15 -> 64 | D14: =Working_Capital!D15 -> 69 | E14: =Working_Capital!E15 -> 62 | F14: =Working_Capital!F15 -> 60
A15: International Sourcing % of Spend | B15: =Sourcing_Model!B19 -> 0.89921387 | C15: =Sourcing_Model!C19 -> 0.89995442 | D15: =Sourcing_Model!C19 -> 0.89995442 | E15: =Sourcing_Model!D19 -> 0.90172312 | F15: =Sourcing_Model!E19 -> 0.90305172
A16: Ending Cash Balance ($) | B16: =Cash_Flow!B21 -> 6379875 | C16: =Cash_Flow!C21 -> 11213957 | D16: =Cash_Flow!D21 -> 10087909 | E16: =Cash_Flow!E21 -> 15508495 | F16: =Cash_Flow!F21 -> 18405426

Sheet Checks
A1: MidWest Precision Components, Inc.
A2: Model Integrity Checks
A4: Check | B4: 2025A | C4: 2026 Budget | D4: 2026 Forecast | E4: 2027 Plan | F4: 2028 Plan | G4: Status
A5: Gross Margin % ties to Assumptions driver | B5: =ROUND('P&L'!B8-Assumptions!C8,4) -> 0 | C5: =ROUND('P&L'!C8-Assumptions!D8,4) -> 0 | D5: =ROUND('P&L'!D8-Assumptions!E8,4) -> 0 | E5: =ROUND('P&L'!E8-Assumptions!F8,4) -> 0 | F5: =ROUND('P&L'!F8-Assumptions!G8,4) -> 0 | G5: =IF(COUNTIF(B5:F5,0)=5,"OK","CHECK") -> OK
A6: Capacity Utilization <= 100% | B6: =Manufacturing_OH!C15 -> 0.9047619 | C6: =Manufacturing_OH!D15 -> 0.89884822 | D6: =Manufacturing_OH!E15 -> 0.94591317 | E6: =Manufacturing_OH!F15 -> 0.94194675 | F6: =Manufacturing_OH!G15 -> 0.93190679 | G6: =IF(COUNTIF(B6:F6,">1")=0,"OK","CHECK") -> OK
A7: Working Capital balances are non-negative | B7: =MIN(Working_Capital!B5:B7) -> 3965893.2 | C7: =MIN(Working_Capital!C5:C7) -> 4245163.7 | D7: =MIN(Working_Capital!D5:D7) -> 4365079.2 | E7: =MIN(Working_Capital!E5:E7) -> 4492070 | F7: =MIN(Working_Capital!F5:F7) -> 4430666.7 | G7: =IF(COUNTIF(B7:F7,"<0")=0,"OK","CHECK: Negative Balance") -> OK
A8: Ending Cash Balance is positive | B8: =Cash_Flow!B21 -> 6379875 | C8: =Cash_Flow!C21 -> 11213957 | D8: =Cash_Flow!D21 -> 10087909 | E8: =Cash_Flow!E21 -> 15508495 | F8: =Cash_Flow!F21 -> 18405426 | G8: =IF(COUNTIF(B8:F8,"<0")=0,"OK","CHECK: Cash Shortfall") -> OK
A9: Depreciation & Amortization is non-negative | B9: =CapEx!B30 -> 200000 | C9: =CapEx!C30 -> 408438.35 | D9: =CapEx!D30 -> 410569.33 | E9: =CapEx!E30 -> 636551.01 | F9: =CapEx!F30 -> 1127792 | G9: =IF(COUNTIF(B9:F9,"<0")=0,"OK","CHECK") -> OK
A10: Revenue Variance Bridge ties out (Budget+Vol+Price=Forecast) | B10: =ROUND(Variance_Drivers!B8+Variance_Drivers!C8+Variance_Drivers!D8-Variance_Drivers!E8,0) -> 0 | G10: =IF(B10=0,"OK","CHECK") -> OK
A11: Bottom-Up COGS Build vs. Top-Down (Assumption-driven) Gross Margin | B11: ='P&L'!B28 -> -26936520 | C11: ='P&L'!C28 -> -28097331 | D11: ='P&L'!D28 -> -28813972 | E11: ='P&L'!E28 -> -29280199 | F11: ='P&L'!F28 -> -29048885 | G11: Known variance — see P&L memo note
A13: Note: The last check above is informational, not a pass/fail check. It quantifies the known gap between the bottom-up labor/material/overhead build and the top-down Gross Margin assumption, caused by the illustrative unit-cost inputs provided in the source sheets.
